kilko_waste/__init__.py
kilko_waste/client.py
kilko_waste/consts.py
kilko_waste/requests.py
kilko_waste/definitions/__init__.py
kilko_waste/definitions/authenticated_request.py
kilko_waste/definitions/balance_response.py
kilko_waste/definitions/config_response.py
kilko_waste/definitions/events_response.py
kilko_waste/definitions/login_request.py
kilko_waste/definitions/login_response.py
kilko_waste/definitions/util.py
kilko_waste-0.1.5.dist-info/METADATA
kilko_waste-0.1.5.dist-info/WHEEL
kilko_waste-0.1.5.dist-info/RECORD
