Metadata-Version: 2.3
Name: kilko_waste
Version: 0.1.5
Summary: Kilko Container Management API Client
Project-URL: Homepage, https://github.com/alinalihassan/Kilko-Container-Management-API
Author-email: Alin Ali Hassan <alinalihassan@gmail.com>
Requires-Python: >=3.12
Requires-Dist: python-dateutil>=2.9.0.post0
Requires-Dist: python-dotenv>=1.0.1
Requires-Dist: requests>=2.32.3
